{
    "decapitation": "D IH K AE P IH T EY SH AH N",
    "dorfman": "D AO R F M AH N",
    "bathrobe": "B AE TH R OW B",
    "kirchner": "K ER K N ER",
    "presidencies": "P R EH Z IH D AH N S IY Z",
    "firefly": "F AY ER F L AY",
    "whitelaw": "HH W AY T L AO",
    "whan": "HH W AE N",
    "uninhabitable": "AH N IH N HH AE B AH T AH B AH L",
    "urethane": "Y ER AH TH EY N",
    "firmest": "F ER M AH S T",
    "csi": "S IY EH S AY",
    "electroplating": "IH L EH K T R AH P L EY T IH NG",
    "pimps": "P IH M P S",
    "recant": "R IY K AE N T",
    "cypriots": "S IH P R IY AA T S",
    "pastoralism": "P AE S T ER AH L IH Z AH M",
    "unveil": "AH N V EY L",
    "workroom": "W ER K R UW M",
    "rehabilitating": "R IY AH B IH L AH T EY T IH NG",
    "barman": "B AA R M AH N",
    "ellwood": "EH L W UH D",
    "sima": "S IY M AH",
    "moyer": "M OY ER",
    "squirm": "S K W ER M",
    "aurea": "AW R EY AA",
    "consolidations": "K AH N S AA L IH D EY SH AH N Z",
    "keizai": "K IY Z EY",
    "raved": "R EY V D",
    "reestablishing": "R IY IH S T AE B L IH SH IH NG",
    "trumped": "T R AH M P T",
    "leveraging": "L EH V ER IH JH IH NG",
    "ambled": "AE M B AH L D",
    "transferability": "T R AE N S F ER AH B IH L IH T IY",
    "surfer": "S ER F ER",
    "opie": "OW P IY",
    "hundredweight": "HH AH N D R AH D W EY T",
    "duplications": "D UW P L IH K EY SH AH N Z",
    "corny": "K AO R N IY",
    "honduran": "HH AA N D UH R AH N",
    "ansari": "AA N S AA R IY",
    "ishii": "IH SH IY IY",
    "engined": "EH N JH AH N D",
    "cyan": "S AY AE N",
    "saponification": "S AH P AA N AH F AH K EY SH AH N",
    "schirmer": "SH ER M ER",
    "gerund": "JH EH R AH N D",
    "gromyko": "G R OW M IY K OW",
    "thanh": "TH AE N",
    "cella": "S EH L AH",
    "resuscitate": "R IY S AH S IH T EY T",
    "cus": "S IY Y UW EH S",
    "listeria": "L IH S T IH R IY AH",
    "hatter": "HH AE T ER",
    "warders": "W AO R D ER Z",
    "sorenson": "S AO R AH N S AH N",
    "enthused": "IH N TH UW Z D",
    "spurring": "S P ER IH NG",
    "cassock": "K AE S AH K",
    "individualists": "IH N D AH V IH JH UW AH L IH S T S",
    "bricklayer": "B R IH K L EY ER",
    "struve": "S T R UW V",
    "hisses": "HH IH S IH Z",
    "coverages": "K AH V R IH JH IH Z",
    "nist": "N IH S T",
    "reuss": "R UW S",
    "plummet": "P L AH M AH T",
    "lucent": "L UW S IH N T",
    "pacemakers": "P EY S M EY K ER Z",
    "allis": "AE L IH S",
    "tubman": "T AH B M AH N",
    "sheepish": "SH IY P IH SH",
    "maritimes": "M AE R AH T AY M Z",
    "auctioned": "AO K SH AH N D",
    "feds": "F EH D Z",
    "wada": "W AA D AH",
    "loreto": "L AO R EH T OW",
    "proselytizing": "P R AA S AH L AH T AY Z IH NG",
    "leal": "L IY L",
    "ugliest": "AH G L IY AH S T",
    "bucher": "B AH K ER",
    "dispelling": "D IH S P EH L IH NG",
    "landfall": "L AE N D F AO L",
    "tequila": "T AH K IY L AH",
    "lynched": "L IH N CH T",
    "latitudinal": "L AE T AH T UW D AH N AH L",
    "heng": "HH EH NG",
    "longitudes": "L AA N JH AH T UW D Z",
    "fells": "F EH L Z",
    "drudge": "D R AH JH",
    "rips": "R IH P S",
    "carat": "K EH R AH T",
    "tota": "T OW T AH",
    "higham": "HH IH G AH M",
    "seng": "S EH NG",
    "taxicab": "T AE K S IY K AE B",
    "dynes": "D AY N Z",
    "measurably": "M EH ZH ER AH B L IY",
    "cornucopia": "K AO R N AH K OW P IY AH",
    "carer": "K EH R ER",
    "buttery": "B AH T ER IY",
    "neurofibromatosis": "N UH R OW F AY B R OW M AH T OW S IH S",
    "okra": "OW K R AH",
    "improbably": "IH M P R AA B AH B L IY",
    "trey": "T R EY",
    "parrott": "P EH R AH T",
    "diez": "D AY AH Z",
    "midterm": "M IH D T ER M",
    "croaking": "K R OW K IH NG",
    "senna": "S EH N AH",
    "hypoglycemic": "HH AY P OW G L AY S IY M IH K",
    "expediting": "EH K S P AH D AY T IH NG",
    "indoctrinated": "IH N D AA K T R AH N EY T IH D",
    "flaunt": "F L AO N T",
    "propping": "P R AA P IH NG",
    "unleashing": "AH N L IY SH IH NG",
    "bullen": "B UH L AH N",
    "oldfield": "OW L D F IY L D",
    "beria": "B EH R IY AH",
    "destabilization": "D IY S T EY B AH L AH Z EY SH AH N",
    "biometric": "B AY AH M EH T R AH K",
    "thrushes": "TH R AH SH IH Z",
    "shipman": "SH IH P M AH N",
    "kamehameha": "K AH M EY AH M EY AH",
    "mercure": "M ER K UH R",
    "platz": "P L AE T S",
    "romp": "R AA M P",
    "zooming": "Z UW M IH NG",
    "breakeven": "B R EY K IY V AH N",
    "rosamund": "R OW Z AH M UH N D",
    "simmonds": "S IH M AH N D Z",
    "decorators": "D EH K ER EY T ER Z",
    "pura": "P Y UH R AH",
    "sharer": "SH EH R ER",
    "fel": "F EH L",
    "fastener": "F AE S N ER",
    "contoured": "K AA N T UH R D",
    "electives": "IH L EH K T IH V Z",
    "pratap": "P R AA T AH P",
    "ophthalmologist": "AA P TH AH M AA L AH JH IH S T",
    "chace": "CH EY S",
    "lethality": "L IY TH AE L AH T IY",
    "arse": "AA R S",
    "macdougall": "M AH K D UW G AH L",
    "erupts": "IH R AH P T S",
    "gird": "G ER D",
    "tokio": "T OW K IY OW",
    "tatiana": "T AE T Y AA N AA",
    "costumed": "K AO S T UW M D",
    "quirky": "K W ER K IY",
    "renovate": "R EH N AH V EY T",
    "corruptible": "K ER AH P T IH B AH L",
    "shunning": "SH AH N IH NG",
    "thousandths": "TH AW Z AH N TH S",
    "excavator": "EH K S K AH V EY T ER",
    "stymied": "S T AY M IY D",
    "kantor": "K AE N T ER",
    "raff": "R AE F",
    "corundum": "K ER AH N D AH M",
    "midair": "M IH D EH R",
    "cobweb": "K AA B W EH B",
    "pompidou": "P AA M P IH D UW",
    "taggart": "T AE G ER T",
    "grubby": "G R AH B IY",
    "subtitled": "S AH B T AY T AH L D",
    "peon": "P IY AH N",
    "rebutted": "R IH B AH T IH D",
    "tomcat": "T AA M K AE T",
    "millikan": "M IH L AH K AH N",
    "seaweeds": "S IY W IY D Z",
    "admonishing": "AE D M AA N IH SH IH NG",
    "persepolis": "P ER S EH P AH L AH S",
    "throttling": "TH R AA T L IH NG",
    "galvez": "G AA L V EH Z",
    "decking": "D EH K IH NG",
    "arkwright": "AA R K R AY T",
    "busses": "B AH S AH Z",
    "referenda": "R EH F ER EH N D AH",
    "snappy": "S N AE P IY",
    "mugabe": "M UW G AA B EY",
    "lozenge": "L AO Z AH N JH",
    "salina": "S AH L IY N AH",
    "heil": "HH AY L",
    "roddy": "R AA D IY",
    "unflagging": "AH N F L AE G IH NG",
    "extenuating": "IH K S T EH N Y UW EY T IH NG",
    "grosz": "G R OW S",
    "restrooms": "R EH S T R UW M Z",
    "dyestuffs": "D AY S T AH F S",
    "crosstalk": "K R AO S T AO K",
    "fessenden": "F EH S AH N D AH N",
    "rudest": "R UW D AH S T",
    "paoli": "P AW L IY",
    "octavio": "AA K T EY V IY OW",
    "galle": "G AE L EY",
    "freeways": "F R IY W EY Z",
    "hendry": "HH EH N D R IY",
    "nowell": "N OW AH L",
    "mccallum": "M AH K AE L AH M",
    "transfused": "T R AE N S F Y UW Z D"
}