{
    "worshippers": "W ER SH IH P ER Z",
    "confining": "K AH N F AY N IH NG",
    "clair": "K L EH R",
    "lurking": "L ER K IH NG",
    "attenuated": "AH T EH N Y UW EY T IH D",
    "israelis": "IH Z R EY L IY Z",
    "maximilian": "M AE K S IH M IH L IY AH N",
    "oxidative": "AA K S AH D AY T IH V",
    "devising": "D IH V AY Z IH NG",
    "departures": "D IH P AA R CH ER Z",
    "bibliographic": "B IH B L IY AA G R AA F IH K",
    "tempt": "T EH M P T",
    "reginald": "R EH JH AH N AH L D",
    "stocked": "S T AA K T",
    "spaniard": "S P AE N Y ER D",
    "blooming": "B L UW M IH NG",
    "lobster": "L AA B S T ER",
    "minors": "M AY N ER Z",
    "listings": "L IH S T IH NG Z",
    "shorten": "SH AO R T AH N",
    "unparalleled": "AH N P EH R AH L EH L D",
    "steamboat": "S T IY M B OW T",
    "misgivings": "M IH S G IH V IH NG Z",
    "datum": "D EY T AH M",
    "sweater": "S W EH T ER",
    "orgasm": "AO R G AE Z AH M",
    "bonnie": "B AA N IY",
    "blooded": "B L AH D IH D",
    "professionalism": "P R AH F EH SH AH N AH L IH Z AH M",
    "bridging": "B R IH JH IH NG",
    "trays": "T R EY Z",
    "forsaken": "F AO R S EY K AH N",
    "kiln": "K IH L N",
    "efficacious": "EH F AH K EY SH AH S",
    "dyer": "D AY ER",
    "lieutenants": "L UW T EH N AH N T S",
    "menopause": "M EH N AH P AW Z",
    "reds": "R EH D Z",
    "prospectus": "P R AH S P EH K T AH S",
    "affixed": "AH F IH K S T",
    "spec": "S P EH K",
    "chanting": "CH AE N T IH NG",
    "summarizing": "S AH M ER AY Z IH NG",
    "speeding": "S P IY D IH NG",
    "regina": "R IH JH IY N AH",
    "mournful": "M AO R N F AH L",
    "andreas": "AA N D R EY AH S",
    "keyword": "K IY W ER D",
    "caption": "K AE P SH AH N",
    "vertices": "V ER T IH S IY Z",
    "reconsider": "R IY K AH N S IH D ER",
    "forcefully": "F AO R S F AH L IY",
    "shudder": "SH AH D ER",
    "sweeps": "S W IY P S",
    "scaffold": "S K AE F AH L D",
    "prefect": "P R IY F EH K T",
    "generative": "JH EH N ER AH T IH V",
    "lyman": "L AY M AH N",
    "laird": "L EH R D",
    "reasonableness": "R IY Z N AH B AH L N AH S",
    "additives": "AE D IH T IH V Z",
    "backdrop": "B AE K D R AA P",
    "allegation": "AE L AH G EY SH AH N",
    "cute": "K Y UW T",
    "lick": "L IH K",
    "australians": "AO S T R EY L Y AH N Z",
    "encyclopaedia": "IH N S AY K L OW P IY D IY AH",
    "forma": "F AO R M AH",
    "lis": "L IH S",
    "insulating": "IH N S AH L EY T IH NG",
    "upbringing": "AH P B R IH NG IH NG",
    "moulding": "M OW L D IH NG",
    "crumbling": "K R AH M B L IH NG",
    "publicized": "P AH B L IH S AY Z D",
    "sawyer": "S OY ER",
    "erroneously": "EH R OW N IY AH S L IY",
    "rheumatism": "R UW M AH T IH Z AH M",
    "unforeseen": "AH N F AO R S IY N",
    "chromosomal": "K R OW M AH S OW M AH L",
    "benefactor": "B EH N AH F AE K T ER",
    "aviv": "AA V IY V",
    "acidosis": "AE S IH D OW S AH S",
    "flaps": "F L AE P S",
    "entrances": "EH N T R AH N S AH Z",
    "intelligently": "IH N T EH L IH JH AH N T L IY",
    "protagonists": "P R OW T AE G AH N AH S T S",
    "exacerbated": "IH G Z AE S ER B EY T IH D",
    "intermediaries": "IH N ER M IY D IY EH R IY Z",
    "narrated": "N EH R EY T IH D",
    "frustrations": "F R AH S T R EY SH AH N Z",
    "erecting": "IH R EH K T IH NG",
    "denunciation": "D IH N AH N S IY EY SH AH N",
    "encryption": "EH N K R IH P SH AH N",
    "churchyard": "CH ER CH Y AA R D",
    "instructing": "IH N S T R AH K T IH NG",
    "quixote": "K IY HH OW T IY",
    "prostrate": "P R AA S T R EY T",
    "particulate": "P ER T IH K Y AH L AH T",
    "abnormally": "AE B N AO R M AH L IY",
    "craftsman": "K R AE F S M AH N",
    "epithet": "EH P AH TH EH T",
    "canberra": "K AE N B EH R AH",
    "refutation": "R EH F Y UW T EY SH AH N",
    "api": "EY P IY AY",
    "fictions": "F IH K SH AH N Z",
    "nbc": "EH N B IY S IY",
    "stereotyped": "S T EH R IY OW T AY P T",
    "beckett": "B EH K IH T",
    "outspoken": "AW T S P OW K AH N",
    "marianne": "M AA R IY AE N",
    "hawks": "HH AO K S",
    "perverted": "P ER V ER T IH D",
    "logarithmic": "L AA G ER IH DH M IH K",
    "atheism": "EY TH IY IH Z AH M",
    "sluggish": "S L AH G IH SH",
    "exaggerate": "IH G Z AE JH ER EY T",
    "refine": "R IH F AY N",
    "insider": "IH N S AY D ER",
    "lessor": "L EH S ER",
    "hitchcock": "HH IH CH K AA K",
    "masking": "M AE S K IH NG",
    "tactile": "T AE K T AY L",
    "molasses": "M AH L AE S AH Z",
    "broadest": "B R AO D IH S T",
    "interiors": "IH N T IH R IY ER Z",
    "cramped": "K R AE M P T",
    "raman": "R AA M AH N",
    "intercepted": "IH N ER S EH P T IH D",
    "policymakers": "P AA L AH S IY M EY K ER Z",
    "gideon": "G IH D IY AH N",
    "drummond": "D R AH M AH N D",
    "signaled": "S IH G N AH L D",
    "barbados": "B AA R B EY D OW S",
    "connector": "K AH N EH K T ER",
    "tuna": "T UW N AH",
    "complicate": "K AA M P L AH K EY T",
    "algiers": "AE L JH IH R Z",
    "consciences": "K AA N CH IH N S IH Z",
    "understandably": "AH N D ER S T AE N D AH B L IY",
    "sufferers": "S AH F ER ER Z",
    "abreast": "AH B R EH S T",
    "colloidal": "K AH L OY D AH L",
    "dolly": "D AA L IY",
    "detectives": "D IH T EH K T IH V Z",
    "loft": "L AO F T",
    "destinies": "D EH S T AH N IY Z",
    "latex": "L EY T EH K S",
    "cds": "S IY D IY Z",
    "overturned": "OW V ER T ER N D",
    "maidens": "M EY D AH N Z",
    "subversion": "S AH B V ER ZH AH N",
    "sill": "S IH L",
    "brevity": "B R EH V AH T IY",
    "dreamer": "D R IY M ER",
    "predictors": "P R IY D IH K T ER Z",
    "northampton": "N AO R TH AE M P T AH N",
    "outwards": "AW T W ER D Z",
    "antisocial": "AE N T AY S OW SH AH L",
    "tectonic": "T EH K T AA N IH K",
    "spartan": "S P AA R T AH N",
    "payoff": "P EY AO F",
    "sausage": "S AO S IH JH",
    "geologists": "JH IY AA L AH JH IH S T S",
    "siberian": "S AY B IH R IY AH N",
    "warships": "W AO R SH IH P S",
    "hack": "HH AE K",
    "darkest": "D AA R K AH S T",
    "permissions": "P ER M IH SH AH N Z",
    "mel": "M EH L",
    "crashing": "K R AE SH IH NG",
    "realistically": "R IY AH L IH S T IH K L IY",
    "pablo": "P AA B L OW",
    "swaying": "S W EY IH NG",
    "patton": "P AE T AH N",
    "mccormick": "M AH K AO R M IH K",
    "chilling": "CH IH L IH NG",
    "alfalfa": "AE L F AE L F AH",
    "settles": "S EH T AH L Z",
    "impenetrable": "IH M P EH N AH T R AH B AH L",
    "negatives": "N EH G AH T IH V Z",
    "tracked": "T R AE K T",
    "sterility": "S T ER IH L IH T IY",
    "squamous": "S K W EY M AH S",
    "reflux": "R IY F L AH K S",
    "throughput": "TH R UW P UH T",
    "lavender": "L AE V AH N D ER",
    "secluded": "S IH K L UW D IH D",
    "spinach": "S P IH N AH CH",
    "unthinkable": "AH N TH IH NG K AH B AH L",
    "phelps": "F EH L P S",
    "roberto": "R OW B EH R T OW",
    "wentworth": "W EH N T W ER TH",
    "subservient": "S AH B S ER V IY AH N T",
    "leaks": "L IY K S",
    "sorely": "S AO R L IY",
    "spade": "S P EY D",
    "coiled": "K OY L D",
    "conceptually": "K AH N S EH P CH UW AH L IY",
    "skiing": "S K IY IH NG",
    "broaden": "B R AO D AH N"
}