{
    "meeting": "M IY T IH NG",
    "clearly": "K L IH R L IY",
    "expected": "IH K S P EH K T IH D",
    "federal": "F EH D R AH L",
    "r": "AA R",
    "nearly": "N IH R L IY",
    "ed": "EH D",
    "extent": "IH K S T EH N T",
    "parents": "P EH R AH N T S",
    "yes": "Y EH S",
    "ideas": "AY D IY AH Z",
    "medical": "M EH D IH K AH L",
    "observed": "AH B Z ER V D",
    "actually": "AE K SH AH L IY",
    "final": "F AY N AH L",
    "george": "JH AO R JH",
    "miles": "M AY AH L Z",
    "elements": "EH L AH M AH N T S",
    "list": "L IH S T",
    "project": "P R AA JH EH K T",
    "product": "P R AA D AH K T",
    "throughout": "TH R UW AW T",
    "christ": "K R AY S T",
    "discussion": "D IH S K AH SH AH N",
    "applied": "AH P L AY D",
    "rules": "R UW L Z",
    "produce": "P R OW D UW S",
    "religion": "R IY L IH JH AH N",
    "deep": "D IY P",
    "operation": "AA P ER EY SH AH N",
    "issues": "IH SH UW Z",
    "else": "EH L S",
    "mass": "M AE S",
    "coming": "K AH M IH NG",
    "determined": "D IH T ER M AH N D",
    "european": "Y UH R AH P IY AH N",
    "events": "IY V EH N T S",
    "security": "S IH K Y UH R AH T IY",
    "oil": "OY L",
    "fine": "F AY N",
    "distance": "D IH S T AH N S",
    "move": "M UW V",
    "effective": "IY F EH K T IH V",
    "paid": "P EY D",
    "nation": "N EY SH AH N",
    "step": "S T EH P",
    "gives": "G IH V Z",
    "success": "S AH K S EH S",
    "literature": "L IH T ER AH CH ER",
    "products": "P R AA D AH K S",
    "neither": "N AY DH ER",
    "resources": "R IY S AO R S IH Z",
    "follow": "F AA L OW",
    "cross": "K R AO S",
    "ask": "AE S K",
    "levels": "L EH V AH L Z",
    "immediately": "IH M IY D IY AH T L IY",
    "certainly": "S ER T AH N L IY",
    "principle": "P R IH N S AH P AH L",
    "moral": "M AO R AH L",
    "july": "JH AH L AY",
    "formed": "F AO R M D",
    "reached": "R IY CH T",
    "faith": "F EY TH",
    "deal": "D IY L",
    "recent": "R IY S AH N T",
    "legal": "L IY G AH L",
    "administration": "AE D M IH N IH S T R EY SH AH N",
    "comes": "K AH M Z",
    "materials": "M AH T IH R IY AH L Z",
    "potential": "P AH T EH N SH AH L",
    "presented": "P R IY Z EH N T IH D",
    "congress": "K AA NG G R AH S",
    "civil": "S IH V AH L",
    "directly": "D IH R EH K L IY",
    "meet": "M IY T",
    "met": "M EH T",
    "principles": "P R IH N S AH P AH L Z",
    "expression": "IH K S P R EH SH AH N",
    "myself": "M AY S EH L F",
    "born": "B AO R N",
    "wide": "W AY D",
    "post": "P OW S T",
    "justice": "JH AH S T IH S",
    "strength": "S T R EH NG TH",
    "relation": "R IY L EY SH AH N",
    "statement": "S T EY T M AH N T",
    "financial": "F AY N AE N SH AH L",
    "dead": "D EH D",
    "larger": "L AA R JH ER",
    "cultural": "K AH L CH ER AH L",
    "historical": "HH IH S T AO R IH K AH L",
    "existence": "IH G Z IH S T AH N S",
    "built": "B IH L T",
    "weight": "W EY T",
    "reference": "R EH F R AH N S",
    "feeling": "F IY L IH NG",
    "round": "R AW N D",
    "reported": "R IH P AO R T IH D",
    "risk": "R IH S K",
    "appeared": "AH P IH R D",
    "included": "IH N K L UW D IH D",
    "scale": "S K EY L",
    "individuals": "IH N D AH V IH JH AH W AH L Z",
    "supply": "S AH P L AY",
    "million": "M IH L Y AH N",
    "differences": "D IH F R AH N S AH Z",
    "write": "R AY T",
    "doubt": "D AW T",
    "hour": "AW R",
    "industrial": "IH N D AH S T R IY AH L",
    "april": "EY P R AH L",
    "primary": "P R AY M EH R IY",
    "base": "B EY S",
    "letters": "L EH T ER Z",
    "interests": "IH N T ER IH S T S",
    "numbers": "N AH M B ER Z",
    "seven": "S EH V AH N",
    "places": "P L EY S IH Z",
    "wall": "W AO L",
    "complex": "K AH M P L EH K S",
    "entire": "IH N T AY ER",
    "try": "T R AY",
    "article": "AA R T IH K AH L",
    "county": "K AW N IY",
    "costs": "K AO S T S",
    "thinking": "TH IH NG K IH NG",
    "record": "R IH K AO R D",
    "flow": "F L OW",
    "follows": "F AA L OW Z",
    "sun": "S AH N",
    "attempt": "AH T EH M P T",
    "bad": "B AE D",
    "instance": "IH N S T AH N S",
    "commission": "K AH M IH SH AH N",
    "easily": "IY Z AH L IY",
    "unit": "Y UW N IH T",
    "died": "D AY D",
    "green": "G R IY N",
    "charles": "CH AA R AH L Z",
    "week": "W IY K",
    "demand": "D IH M AE N D",
    "acid": "AE S IH D",
    "environment": "IH N V AY R AH N M AH N T",
    "proper": "P R AA P ER",
    "takes": "T EY K S",
    "positive": "P AA Z AH T IH V",
    "talk": "T AO K",
    "active": "AE K T IH V",
    "image": "IH M IH JH",
    "plant": "P L AE N T",
    "freedom": "F R IY D AH M",
    "library": "L AY B R EH R IY",
    "dark": "D AA R K",
    "key": "K IY",
    "mentioned": "M EH N SH AH N D",
    "co": "K OW",
    "speak": "S P IY K",
    "allowed": "AH L AW D",
    "whatever": "HH W AH T EH V ER",
    "concerned": "K AH N S ER N D",
    "measure": "M EH ZH ER",
    "lives": "L AY V Z",
    "merely": "M IH R L IY",
    "fear": "F IH R",
    "paris": "P AE R IH S",
    "independent": "IH N D IH P EH N D AH N T",
    "heat": "HH IY T",
    "circumstances": "S ER K AH M S T AE N S IH Z",
    "thomas": "T AA M AH S",
    "giving": "G IH V IH NG",
    "master": "M AE S T ER",
    "tried": "T R AY D",
    "china": "CH AY N AH",
    "eye": "AY",
    "upper": "AH P ER",
    "gone": "G AO N",
    "actual": "AE K SH AH L",
    "cold": "K OW L D",
    "frequently": "F R IY K W EH N T L IY",
    "eight": "EY T",
    "ability": "AH B IH L AH T IY",
    "unless": "AH N L EH S",
    "regard": "R IH G AA R D",
    "henry": "HH EH N R IY",
    "status": "S T EY T AH S",
    "hear": "HH IY R",
    "thousand": "TH AW Z AH N",
    "minutes": "M IH N AH T S",
    "parties": "P AA R T IY Z",
    "stock": "S T AA K",
    "student": "S T UW D AH N T",
    "rise": "R AY Z",
    "arms": "AA R M Z",
    "factor": "F AE K T ER",
    "charge": "CH AA R JH",
    "easy": "IY Z IY",
    "created": "K R IY EY T IH D",
    "stand": "S T AE N D",
    "started": "S T AA R T IH D"
}