{
    "appallingly": "AH P AO L IH NG L IY",
    "bulmer": "B AH L M ER",
    "hijackers": "HH AY JH AE K ER Z",
    "bravura": "B R AH V Y UH R AH",
    "hashim": "HH AE SH IH M",
    "sealants": "S IY L AH N T S",
    "whittlesey": "HH W IH T AH L S IY",
    "hodgkinson": "HH AA JH K IH N S AH N",
    "hindquarters": "HH AY N D K W AO R T ER Z",
    "carbonized": "K AA R B AH N AY Z D",
    "farrand": "F AE R AH N D",
    "skyrocketed": "S K AY R AA K AH T IH D",
    "overwrite": "OW V ER R AY T",
    "ruggiero": "R UW JH IH R OW",
    "wege": "W IY JH",
    "polyamide": "P AA L IY AE M AY D",
    "honeybee": "HH AH N IY B IY",
    "beady": "B IY D IY",
    "lakewood": "L EY K W UH D",
    "respirators": "R EH S P ER EY T ER Z",
    "feeney": "F IY N IY",
    "ruf": "R AH F",
    "browed": "B R AW D",
    "transvestite": "T R AE N Z V EH S T AY T",
    "accolades": "AE K AH L EY D Z",
    "ema": "IY M AH",
    "ambrogio": "AE M B R OW JH IY OW",
    "samir": "S AA M IH R",
    "ried": "R IY D",
    "battelle": "B AH T EH L",
    "hangars": "HH AE NG ER Z",
    "lunchroom": "L AH N CH R UW M",
    "callas": "K AE L AH Z",
    "bagpipes": "B AE G P AY P S",
    "whaley": "HH W EY L IY",
    "refreshingly": "R IY F R EH SH IH NG L IY",
    "kutch": "K AH CH",
    "lafollette": "L AA F AH L EH T",
    "consiglio": "K AA N S IY G L IY OW",
    "deltaic": "D EH L T EY IH K",
    "babyhood": "B EY B IY HH UH D",
    "verner": "V ER N ER",
    "schapiro": "SH AE P AY R OW",
    "guillen": "G IH L AH N",
    "mattson": "M AE T S AH N",
    "monoplane": "M AA N AH P L EY N",
    "heilman": "HH AY L M AH N",
    "effervescent": "EH F ER V EH S AH N T",
    "fabio": "F AA B IY OW",
    "michell": "M IH CH AH L",
    "chillies": "CH IH L IY Z",
    "overpriced": "OW V ER P R AY S T",
    "minimalism": "M IH N AH M AH L IH Z AH M",
    "billionaire": "B IH L Y AH N EH R",
    "wiebe": "W IY B",
    "castille": "K AE S T IH L",
    "dowell": "D AA W EH L",
    "rooke": "R UH K",
    "holtz": "HH OW L T S",
    "iversen": "IH V ER S AH N",
    "sugden": "S AH G D AH N",
    "leverett": "L EH V ER EH T",
    "bott": "B AA T",
    "cogeneration": "K OW JH EH N ER EY SH AH N",
    "snuck": "S N AH K",
    "viviparous": "V AY V IH P ER AH S",
    "squibb": "S K W IH B",
    "ater": "EY T ER",
    "critters": "K R IH T ER Z",
    "holmberg": "HH OW L M B ER G",
    "donohue": "D AA N AH Y UW",
    "donuts": "D OW N AH T S",
    "luhmann": "L AH M AH N",
    "disqualifying": "D IH S K W AA L AH F AY IH NG",
    "magno": "M AE G N OW",
    "enchanter": "EH N CH AE N T ER",
    "prue": "P R UW",
    "castellanos": "K AA S T EY L AA N OW Z",
    "meandered": "M IY AE N D ER D",
    "finisher": "F IH N IH SH ER",
    "donnan": "D AA N AH N",
    "seifert": "S AY F ER T",
    "siegmund": "S IY G M AH N D",
    "fragmenting": "F R AE G M EH N T IH NG",
    "disappointingly": "D IH S AH P OY N IH NG L IY",
    "blotched": "B L AA T CH T",
    "oryx": "AO R IH K S",
    "ladles": "L EY D AH L Z",
    "hadden": "HH AE D AH N",
    "fluor": "F L UW ER",
    "geodesy": "JH IY AA D AH S IY",
    "jibe": "JH AY B",
    "glamor": "G L AE M ER",
    "internationalists": "IH N T ER N AE SH AH N AA L IH S T S",
    "findley": "F IH N D L IY",
    "masterman": "M AE S T ER M AH N",
    "imponderable": "IH M P AA N D ER AH B AH L",
    "backtrack": "B AE K T R AE K",
    "bowmen": "B OW M AH N",
    "polluter": "P AH L UW T ER",
    "flavia": "F L AE V IY AH",
    "retailed": "R IY T EY L D",
    "redlich": "R EH D L IH K",
    "gaucher": "G OW SH ER",
    "tannen": "T AE N AH N",
    "dasa": "D AE S AH",
    "jailers": "JH EY L ER Z",
    "faris": "F EH R IH S",
    "norske": "N AO R S K IY",
    "vieira": "V IY EH R AH",
    "thacher": "TH AE K ER",
    "himmel": "HH IH M AH L",
    "embellishing": "EH M B EH L IH SH IH NG",
    "cheerleaders": "CH IH R L IY D ER Z",
    "videoconferencing": "V IY D IY OW K AA N F R AH N S IH NG",
    "amaranth": "AE M ER AE N TH",
    "hulking": "HH AH L K IH NG",
    "yesteryear": "Y EH S T ER Y IH R",
    "stratus": "S T R AE T AH S",
    "petered": "P IY T ER D",
    "vivienne": "V IH V IY AH N",
    "spokespersons": "S P OW K S P ER S AH N Z",
    "gaddis": "G AE D IH S",
    "wrangler": "R AE NG G L ER",
    "nava": "N AA V AH",
    "toma": "T OW M AH",
    "volney": "V OW L N IY",
    "disables": "D IH S EY B AH L Z",
    "damas": "D AA M AH Z",
    "brae": "B R EY",
    "mylar": "M AY L AA R",
    "whys": "HH W AY Z",
    "leopoldo": "L IY AH P OW L D OW",
    "ueda": "UW EY D AH",
    "mccrae": "M AH K R EY",
    "mcreynolds": "M AH K R EY N AH L D Z",
    "gerardo": "JH ER AA R D OW",
    "wolman": "W AA L M AH N",
    "cadell": "K AA D EY L",
    "yearlings": "Y IH L IH NG Z",
    "octahedron": "AA K T AH HH IY D R AH N",
    "citywide": "S IH T IY W AY D",
    "mordechai": "M AO R D AH K AY",
    "biltmore": "B IH L T M AO R",
    "vroom": "V R UW M",
    "lamia": "L EY M IY AH",
    "lida": "L IY D AH",
    "sicken": "S IH K AH N",
    "intermingle": "IH N T ER M IH NG G AH L",
    "cicada": "S AH K EY D AH",
    "shader": "SH EY D ER",
    "lucida": "L UW CH IY D AH",
    "gelder": "G EH L D ER",
    "burchell": "B ER K AH L",
    "aesthete": "EH S TH IY T",
    "silber": "S IH L B ER",
    "lobos": "L OW B OW S",
    "belasco": "B EH L AA S K OW",
    "zell": "Z EH L",
    "cajoling": "K AH JH OW L IH NG",
    "hedrick": "HH EH D R IH K",
    "haverford": "HH AE V ER F ER D",
    "calisthenics": "K AE L AH S TH EH N IH K S",
    "pawtucket": "P AO T AH K IH T",
    "chucked": "CH AH K T",
    "defeatist": "D IH F IY T IH S T",
    "grigg": "G R IH G",
    "undine": "AH N D IY N",
    "purloined": "P ER L OY N D",
    "survivability": "S ER V AY V AH B IH L IH T IY",
    "hibbard": "HH IH B ER D",
    "extorting": "EH K S T AO R T IH NG",
    "overvaluation": "OW V ER V AE L Y UW EY SH AH N",
    "toting": "T OW T IH NG",
    "mauser": "M AW S ER",
    "detainee": "D IY T EY N IY",
    "meritocracy": "M EH R IH T AO K R AH S IY",
    "fitt": "F IH T",
    "magnifications": "M AE G N AH F AH K EY SH AH N Z",
    "alene": "AH L IY N",
    "distiller": "D IH S T IH L ER",
    "allerton": "AE L ER T AH N",
    "bren": "B R EH N",
    "pellegrini": "P EH L EH G R IY N IY",
    "skeptically": "S K EH P T IH K L IY",
    "leong": "L EH NG",
    "creditworthiness": "K R EH D IH T W ER DH IY N AH S",
    "kath": "K AE TH",
    "onsite": "AA N S AY T",
    "baskin": "B AE S K IH N",
    "eban": "IY B AH N",
    "gimmicks": "G IH M IH K S",
    "staunchest": "S T AO N CH AH S T",
    "freezers": "F R IY Z ER Z",
    "gunny": "G AH N IY",
    "xenia": "Z IY N IY AH",
    "modesto": "M OW D EH S T OW",
    "underage": "AH N D ER IH JH",
    "braverman": "B R EY V ER M AH N",
    "impoundment": "IH M P AW N D M AH N T"
}