{
    "neglect": "N IH G L EH K T",
    "flood": "F L AH D",
    "motivation": "M OW T AH V EY SH AH N",
    "lane": "L EY N",
    "lawyers": "L OY ER Z",
    "hanging": "HH AE NG G IH NG",
    "motive": "M OW T IH V",
    "correctly": "K ER EH K T L IY",
    "nerves": "N ER V Z",
    "upward": "AH P W ER D",
    "assembled": "AH S EH M B AH L D",
    "clock": "K L AA K",
    "feared": "F IH R D",
    "associates": "AH S OW SH IY EY T S",
    "deck": "D EH K",
    "sooner": "S UW N ER",
    "explore": "IH K S P L AO R",
    "ing": "IH NG",
    "wisconsin": "W IH S K AA N S AH N",
    "mighty": "M AY T IY",
    "neglected": "N IH G L EH K T IH D",
    "themes": "TH IY M Z",
    "seats": "S IY T S",
    "reprinted": "R IY P R IH N T IH D",
    "islam": "IH S L AA M",
    "grows": "G R OW Z",
    "shorter": "SH AO R T ER",
    "availability": "AH V EY L AH B IH L IH T IY",
    "armies": "AA R M IY Z",
    "beer": "B IH R",
    "movie": "M UW V IY",
    "farming": "F AA R M IH NG",
    "anglo": "AE NG G L OW",
    "knife": "N AY F",
    "mature": "M AH T Y UH R",
    "argues": "AA R G Y UW Z",
    "technologies": "T EH K N AA L AH JH IY Z",
    "somebody": "S AH M B AH D IY",
    "recalled": "R IH K AO L D",
    "sampling": "S AE M P L IH NG",
    "preface": "P R EH F AH S",
    "dancing": "D AE N S IH NG",
    "badly": "B AE D L IY",
    "ridge": "R IH JH",
    "alternatives": "AO L T ER N AH T IH V Z",
    "preservation": "P R EH Z ER V EY SH AH N",
    "defeated": "D IH F IY T IH D",
    "liberation": "L IH B ER EY SH AH N",
    "rigid": "R IH JH IH D",
    "surrender": "S ER EH N D ER",
    "archives": "AA R K AY V Z",
    "manners": "M AE N ER Z",
    "mobile": "M OW B AH L",
    "criterion": "K R AY T IH R IY AH N",
    "hitherto": "HH IH DH ER T UW",
    "associate": "AH S OW SH IY EY T",
    "deficiency": "D IH F IH SH AH N S IY",
    "lens": "L EH N Z",
    "reception": "R IY S EH P SH AH N",
    "publisher": "P AH B L IH SH ER",
    "pointing": "P OY N T IH NG",
    "novels": "N AA V AH L Z",
    "ct": "K AO R T",
    "rebellion": "R IH B EH L Y AH N",
    "excuse": "IH K S K Y UW Z",
    "li": "L IY",
    "grammar": "G R AE M ER",
    "abundant": "AH B AH N D AH N T",
    "manifest": "M AE N AH F EH S T",
    "earned": "ER N D",
    "appreciate": "AH P R IY SH IY EY T",
    "hi": "HH AY",
    "deputy": "D EH P Y UW T IY",
    "historian": "HH IH S T AO R IY AH N",
    "commands": "K AH M AE N D Z",
    "commanded": "K AH M AE N D IH D",
    "organism": "AO R G AH N IH Z AH M",
    "informal": "IH N F AO R M AH L",
    "lover": "L AH V ER",
    "certificate": "S ER T IH F IH K AH T",
    "imagined": "IH M AE JH AH N D",
    "bob": "B AA B",
    "pakistan": "P AE K IH S T AE N",
    "aristotle": "EH R AH S T AA T AH L",
    "detected": "D IH T EH K T IH D",
    "jefferson": "JH EH F ER S AH N",
    "everyday": "EH V R IY D EY",
    "keeps": "K IY P S",
    "invention": "IH N V EH N SH AH N",
    "politicians": "P AA L AH T IH SH AH N Z",
    "sociology": "S OW S IY AA L AH JH IY",
    "belt": "B EH L T",
    "bias": "B AY AH S",
    "perfection": "P ER F EH K SH AH N",
    "gordon": "G AO R D AH N",
    "dad": "D AE D",
    "sentiment": "S EH N AH M AH N T",
    "riding": "R AY D IH NG",
    "protocol": "P R OW T AH K AO L",
    "specialized": "S P EH SH AH L AY Z D",
    "lung": "L AH NG",
    "races": "R EY S IH Z",
    "responded": "R IY S P AA N D IH D",
    "photograph": "F OW T AH G R AE F",
    "suspended": "S AH S P EH N D IH D",
    "suicide": "S UW IH S AY D",
    "voting": "V OW T IH NG",
    "renal": "R IY N AH L",
    "lots": "L AA T S",
    "rises": "R AY Z IH Z",
    "visiting": "V IH Z IH T IH NG",
    "checked": "CH EH K T",
    "impressed": "IH M P R EH S T",
    "capitalism": "K AE P IH T AH L IH Z AH M",
    "registration": "R EH JH IH S T R EY SH AH N",
    "managing": "M AE N AH JH IH NG",
    "demonstration": "D EH M AH N S T R EY SH AH N",
    "sheets": "SH IY T S",
    "baltimore": "B AO L T AH M AO R",
    "static": "S T AE T IH K",
    "behaviors": "B IH HH EY V Y ER Z",
    "prize": "P R AY Z",
    "pitch": "P IH CH",
    "immigration": "IH M AH G R EY SH AH N",
    "capitalist": "K AE P AH T AH L IH S T",
    "listened": "L IH S AH N D",
    "variance": "V EH R IY AH N S",
    "wright": "R AY T",
    "justification": "JH AH S T AH F AH K EY SH AH N",
    "perceive": "P ER S IY V",
    "handsome": "HH AE N S AH M",
    "singular": "S IH NG G Y AH L ER",
    "tie": "T AY",
    "immigrants": "IH M AH G R AH N T S",
    "acknowledge": "AE K N AA L IH JH",
    "subjective": "S AH B JH EH K T IH V",
    "federation": "F EH D ER EY SH AH N",
    "bold": "B OW L D",
    "socialism": "S OW SH AH L IH Z AH M",
    "filed": "F AY L D",
    "landed": "L AE N D IH D",
    "sessions": "S EH SH AH N Z",
    "contacts": "K AA N T AE K S",
    "filling": "F IH L IH NG",
    "unnecessary": "AH N N EH S AH S EH R IY",
    "stimulation": "S T IH M Y AH L EY SH AH N",
    "eager": "IY G ER",
    "dawn": "D AO N",
    "princess": "P R IH N S EH S",
    "presidential": "P R EH Z IH D EH N SH AH L",
    "streams": "S T R IY M Z",
    "pine": "P AY N",
    "electrons": "IH L EH K T R AA N Z",
    "producers": "P R AH D UW S ER Z",
    "pa": "P AA",
    "physiological": "F IH Z IY AH L AA JH IH K AH L",
    "combat": "K AH M B AE T",
    "princeton": "P R IH N S T AH N",
    "inspiration": "IH N S P ER EY SH AH N",
    "butter": "B AH T ER",
    "geographical": "JH IY AH G R AE F IH K AH L",
    "nearest": "N IH R AH S T",
    "flexible": "F L EH K S AH B AH L",
    "knees": "N IY Z",
    "netherlands": "N EH DH ER L AH N D Z",
    "meanings": "M IY N IH NG Z",
    "expenditures": "IH K S P EH N D IH CH ER Z",
    "landing": "L AE N D IH NG",
    "wedding": "W EH D IH NG",
    "sizes": "S AY Z IH Z",
    "package": "P AE K IH JH",
    "angel": "EY N JH AH L",
    "historians": "HH IH S T AO R IY AH N Z",
    "dean": "D IY N",
    "perspectives": "P ER S P EH K T IH V Z",
    "suspect": "S AH S P EH K T",
    "marx": "M AA R K S",
    "recover": "R IH K AH V ER",
    "smell": "S M EH L",
    "abraham": "EY B R AH HH AE M",
    "cents": "S EH N S",
    "governmental": "G AH V ER N M EH N T AH L",
    "thompson": "T AA M S AH N",
    "sweden": "S W IY D AH N",
    "soils": "S OY L Z",
    "paintings": "P EY N IH NG Z",
    "accurately": "AE K Y ER AH T L IY",
    "thereafter": "DH EH R AE F T ER",
    "sport": "S P AO R T",
    "zealand": "Z IY L AH N D",
    "boxes": "B AA K S IH Z",
    "rod": "R AA D",
    "online": "AO N L AY N",
    "verb": "V ER B",
    "modification": "M AA D AH F AH K EY SH AH N",
    "locations": "L OW K EY SH AH N Z",
    "assess": "AH S EH S",
    "aggressive": "AH G R EH S IH V",
    "lakes": "L EY K S",
    "bishops": "B IH SH AH P S"
}