{
    "greenbacks": "G R IY N B AE K S",
    "freda": "F R EH D",
    "outpatients": "AW T P EY SH AH N T S",
    "westernization": "W EH S T ER N IH Z EY SH AH N",
    "kingfisher": "K IH NG F IH SH ER",
    "magus": "M EY G AH S",
    "grates": "G R EY T S",
    "laszlo": "L AE Z L OW",
    "crump": "K R AH M P",
    "wallowing": "W AA L OW IH NG",
    "lowndes": "L OW N D Z",
    "stillborn": "S T IH L B AO R N",
    "banister": "B AE N IH S T ER",
    "mangoes": "M AE NG G OW Z",
    "popham": "P AA F AH M",
    "strutting": "S T R AH T IH NG",
    "cheyennes": "SH AY EH N Z",
    "formalize": "F AO R M AH L AY Z",
    "chromatogram": "K R OW M AE T AH G R AE M",
    "kempe": "K EH M P",
    "townsfolk": "T AW N Z F OW K",
    "repartee": "R EH P ER T IY",
    "quadrupled": "K W AA D R UW P AH L D",
    "disciplinarian": "D IH S IH P L IH N EH R IY AH N",
    "updike": "AH P D AY K",
    "cabral": "K AE B R AH L",
    "elmo": "EH L M OW",
    "mormonism": "M AO R M AH N IH Z AH M",
    "macmahon": "M AH K M AE N",
    "creel": "K R IY L",
    "hampers": "HH AE M P ER Z",
    "entrusting": "EH N T R AH S T IH NG",
    "orphanages": "AO R F AH N IH JH IH Z",
    "mignon": "M IH G N AH N",
    "babbage": "B AE B IH JH",
    "onetime": "W AH N T AY M",
    "constricting": "K AH N S T R IH K T IH NG",
    "bol": "B AA L",
    "corregidor": "K ER EH G AH D AO R",
    "seamstress": "S IY M S T R IH S",
    "ratcliffe": "R AE T K L IH F",
    "behaviorally": "B IY HH EY V Y ER AH L IY",
    "adamantly": "AE D AH M AH N T L IY",
    "clonidine": "K L AA N IH D IY N",
    "metall": "M EH T AO L",
    "baht": "B AA T",
    "uninvolved": "AH N IH N V AO L V D",
    "haye": "HH EY",
    "impinges": "IH M P IH N JH IH Z",
    "ministration": "M IH N AH S T R EY SH AH N",
    "passersby": "P AE S ER Z B IY",
    "braxton": "B R AE K S T AH N",
    "congealed": "K AH N JH IY L D",
    "disservice": "D IH S ER V AH S",
    "newsroom": "N UW Z R UW M",
    "herbst": "HH ER B S T",
    "faking": "F EY K IH NG",
    "thursdays": "TH ER Z D IY Z",
    "slanders": "S L AE N D ER Z",
    "oba": "OW B AH",
    "escobar": "EH S K AH B AA R",
    "nicosia": "N IH K AH S IY AH",
    "smearing": "S M IH R IH NG",
    "invigorated": "IH N V IH G ER EY T IH D",
    "weedy": "W IY D IY",
    "ayr": "EY R",
    "therapeutically": "TH EH R AH P Y UW T IH K L IY",
    "bookshelf": "B UH K SH EH L F",
    "buford": "B Y UW F ER D",
    "arbiters": "AA R B AH T ER Z",
    "prancing": "P R AE N S IH NG",
    "jeeps": "JH IY P S",
    "seeger": "S IY G ER",
    "illiterates": "IH L IH T ER AH T S",
    "prohibitory": "P R OW HH IH B AH T AO R IY",
    "gladiator": "G L AE D IY EY T ER",
    "komsomol": "K AA M S OW M AH L",
    "regimentation": "R EH JH AH M EH N T EY SH AH N",
    "reassuringly": "R IY AH SH UH R IH NG L IY",
    "decennial": "D AH S EH N IY AH L",
    "fielder": "F IY L D ER",
    "polygyny": "P AH L IH JH AH N IY",
    "troth": "T R AO TH",
    "zora": "Z AO R AH",
    "hoeing": "HH OW IH NG",
    "ebbed": "EH B AH D",
    "basketry": "B AE S K AH T R IY",
    "likens": "L AY K AH N Z",
    "underwritten": "AH N D ER R IH T AH N",
    "radiologist": "R EY D IY AA L AH JH IH S T",
    "anglophone": "AE N G L AH F OW N",
    "anaconda": "AE N AH K AA N D AH",
    "stockman": "S T AA K M AH N",
    "renard": "R IH N AA R D",
    "knott": "N AA T",
    "soli": "S OW L IY",
    "wais": "W EY Z",
    "joist": "JH OY S T",
    "weissman": "W AY S M AH N",
    "yancey": "Y AE N S IY",
    "toning": "T OW N IH NG",
    "scabs": "S K AE B Z",
    "hiked": "HH AY K T",
    "peebles": "P IY B AH L Z",
    "neuer": "N OY ER",
    "consign": "K AH N S AY N",
    "nicolaus": "N IH K AO L AW Z",
    "spas": "S P AA Z",
    "betsey": "B EH T S IY",
    "ferrier": "F EH R IY ER",
    "tilton": "T IH L T AH N",
    "culvert": "K AH L V ER T",
    "scooter": "S K UW T ER",
    "gothenburg": "G AA T AH N B ER G",
    "noam": "N OW M",
    "dae": "D EY",
    "noh": "N OW",
    "woolsey": "W UH L Z IY",
    "rothstein": "R AO TH S T IY N",
    "dorr": "D AO R",
    "carman": "K AA R M AH N",
    "confounds": "K AH N F AW N D Z",
    "dubai": "D UW B AY",
    "staat": "S T AA T",
    "jamb": "JH AE M",
    "diablo": "D IY AE B L OW",
    "camshaft": "K AE M SH AE F T",
    "imminence": "IH M AH N AH N S",
    "bache": "B EY CH",
    "eloise": "EH L OW IY Z",
    "hydrogenated": "HH AY D R AA JH AH N EY T IH D",
    "ionospheric": "AY AA N AO S F EH R IH K",
    "squealing": "S K W IY L IH NG",
    "nav": "N AE V",
    "hubbell": "HH AH B AH L",
    "rockford": "R AA K F ER D",
    "brazos": "B R AA Z OW S",
    "ammo": "AE M OW",
    "steinmetz": "S T AY N M EH T S",
    "blindfold": "B L AY N D F OW L D",
    "vibrator": "V AY B R EY T ER",
    "grosso": "G R OW S OW",
    "vicomte": "V IH K AA M T",
    "obstetricians": "AA B S T AH T R IH SH AH N Z",
    "graff": "G R AE F",
    "putney": "P AH T N IY",
    "clairvoyant": "K L EH R V OY AH N T",
    "bestseller": "B EH S EH L ER",
    "groat": "G R OW T",
    "macrae": "M AH K R EY",
    "karp": "K AA R P",
    "banff": "B AE N F",
    "rathbone": "R AE TH B OW N",
    "descents": "D IH S EH N T S",
    "boland": "B OW L AH N D",
    "conkling": "K AA NG K L IH NG",
    "marsupials": "M AA R S UW P IY AH L S",
    "aliases": "EY L IY AH S IH Z",
    "perspiring": "P ER S P AY R IH NG",
    "interlock": "IH N T ER L AA K",
    "relive": "R IY L IH V",
    "unwed": "AH N W EH D",
    "technologist": "T EH K N AA L AH JH IH S T",
    "unnerving": "AH N ER V IH NG",
    "phoebus": "F IY B AH S",
    "smokeless": "S M OW K L AH S",
    "whitewater": "HH W AY T W AO T ER",
    "diorite": "D AY ER AY T",
    "rueful": "R UW F AH L",
    "rill": "R IH L",
    "skyward": "S K AY W ER D",
    "pape": "P EY P",
    "arthropod": "AA R TH R AH P AA D",
    "overvalued": "OW V ER V AE L Y UW D",
    "drafters": "D R AE F T ER Z",
    "tiananmen": "T IY EH N AE N M EH N",
    "kenton": "K EH N T AH N",
    "innately": "IH N EY T L IY",
    "royall": "R OY AH L",
    "mucho": "M UW CH OW",
    "homeopathy": "HH OW M IY OW P AE TH IY",
    "animations": "AE N AH M EY SH AH N Z",
    "tatum": "T EY T AH M",
    "sephardic": "S AH F AA R D IH K",
    "ravaging": "R AE V IH JH IH NG",
    "carousel": "K EH R AH S EH L",
    "linde": "L IH N D",
    "prichard": "P R IH CH ER D",
    "quieting": "K W AY AH T IH NG",
    "medford": "M EH D F ER D",
    "renfrew": "R EH N F R UW",
    "moldings": "M OW L D IH NG Z",
    "landsat": "L AE N D S AE T",
    "harkness": "HH AA R K N AH S",
    "epitaphs": "EH P AH T AE F S",
    "rhizomes": "R AY Z OW M Z",
    "workbench": "W ER K B EH N CH",
    "refresher": "R IH F R EH SH ER",
    "hollingsworth": "HH AA L IH NG Z W ER TH",
    "hispano": "HH IH S P AA N OW"
}